.coveragerc
LICENSE
MANIFEST.in
README.md
dev_requirements.txt
requirements.txt
setup.cfg
setup.py
versioneer.py
csirtg_enrichment/__init__.py
csirtg_enrichment/_version.py
csirtg_enrichment/constants.py
csirtg_enrichment/utils.py
csirtg_enrichment.egg-info/PKG-INFO
csirtg_enrichment.egg-info/SOURCES.txt
csirtg_enrichment.egg-info/dependency_links.txt
csirtg_enrichment.egg-info/entry_points.txt
csirtg_enrichment.egg-info/requires.txt
csirtg_enrichment.egg-info/top_level.txt
csirtg_enrichment/plugins/__init__.py
csirtg_enrichment/plugins/geo.py
csirtg_enrichment/plugins/peers.py
test/test_basics.py