Metadata-Version: 1.1
Name: csirtg-enrichment
Version: 0.0a1
Summary: CSIRTG enrichment Framework
Home-page: https://github.com/csirtgadgets/csirtg-enrichment
Author: Wes Young
Author-email: wes@csirtgadgets.com
License: MPL2
Keywords: security
Platform: UNKNOWN
Classifier: Programming Language :: Python
